fastMONAI/__init__.py
fastMONAI/_modidx.py
fastMONAI/dataset_info.py
fastMONAI/external_data.py
fastMONAI/research_utils.py
fastMONAI/utils.py
fastMONAI/vision_all.py
fastMONAI/vision_augmentation.py
fastMONAI/vision_core.py
fastMONAI/vision_data.py
fastMONAI/vision_inference.py
fastMONAI/vision_loss.py
fastMONAI/vision_metrics.py
fastMONAI/vision_patch.py
fastMONAI/vision_plot.py
fastmonai-0.5.4.dist-info/licenses/LICENSE
fastmonai-0.5.4.dist-info/METADATA
fastmonai-0.5.4.dist-info/WHEEL
fastmonai-0.5.4.dist-info/entry_points.txt
fastmonai-0.5.4.dist-info/top_level.txt
fastmonai-0.5.4.dist-info/RECORD
