Metadata-Version: 2.4
Name: fastMONAI
Version: 0.5.4
Summary: fastMONAI library
Home-page: https://github.com/MMIV-ML/fastMONAI
Author: Satheshkumar Kaliyugarasan
Author-email: skaliyugarasan@hotmail.com
License: Apache Software License 2.0
Keywords: deep learning,medical imaging
Classifier: Development Status :: 3 - Alpha
Classifier: Intended Audience :: Developers
Classifier: Natural Language :: English
Classifier: Programming Language :: Python :: 3.10
Classifier: Programming Language :: Python :: 3.11
Classifier: Programming Language :: Python :: 3.12
Classifier: License :: OSI Approved :: Apache Software License
Requires-Python: >=3.10
License-File: LICENSE
Requires-Dist: fastai==2.8.3
Requires-Dist: monai==1.5.0
Requires-Dist: torchio==0.20.19
Requires-Dist: xlrd>=1.2.0
Requires-Dist: scikit-image==0.25.2
Requires-Dist: imagedata==3.8.14
Requires-Dist: mlflow==3.3.1
Requires-Dist: huggingface-hub
Requires-Dist: gdown
Requires-Dist: gradio
Requires-Dist: opencv-python
Requires-Dist: plum-dispatch
Provides-Extra: dev
Requires-Dist: ipywidgets; extra == "dev"
Requires-Dist: nbdev; extra == "dev"
Requires-Dist: tabulate; extra == "dev"
Requires-Dist: quarto; extra == "dev"
Dynamic: author
Dynamic: author-email
Dynamic: classifier
Dynamic: description
Dynamic: description-content-type
Dynamic: home-page
Dynamic: keywords
Dynamic: license
Dynamic: license-file
Dynamic: provides-extra
Dynamic: requires-dist
Dynamic: requires-python
Dynamic: summary
